{
  "ImageFilePath": "Synthetic_70.jpg",
  "Carts": [
    {
      "BodyCenter": "225, -225",
      "BodyWidth": 129,
      "BodyHeight": 57,
      "Angle": -0.5017822
    }
  ],
  "Balls": [
    {
      "Center": "225, -675",
      "Radius": 129.375,
      "IsStatic": false
    }
  ],
  "Walls": [],
  "Blocks": [],
  "Lines": [],
  "Springs": [
    {
      "A": "675, -225",
      "B": "654, -97"
    }
  ],
  "Triangles": [
    {
      "A": "605, -783",
      "B": "-24, 309",
      "C": "172, 0",
      "Angle": -0.03926991
    }
  ]
}