{
  "ImageFilePath": "Synthetic_60.jpg",
  "Carts": [
    {
      "BodyCenter": "225, -225",
      "BodyWidth": 110,
      "BodyHeight": 68,
      "Angle": 0.152716309
    }
  ],
  "Balls": [
    {
      "Center": "225, -675",
      "Radius": 110.625,
      "IsStatic": false
    }
  ],
  "Walls": [],
  "Blocks": [],
  "Lines": [],
  "Springs": [
    {
      "A": "675, -225",
      "B": "566, -242"
    }
  ],
  "Triangles": [
    {
      "A": "582, -746",
      "B": "2, 264",
      "C": "205, 0",
      "Angle": 0.004363323
    }
  ]
}