{
  "ImageFilePath": "Synthetic_31.jpg",
  "Carts": [
    {
      "BodyCenter": "225, -225",
      "BodyWidth": 131,
      "BodyHeight": 56,
      "Angle": -0.567232
    }
  ],
  "Balls": [
    {
      "Center": "225, -675",
      "Radius": 131.25,
      "IsStatic": false
    }
  ],
  "Walls": [],
  "Blocks": [
    {
      "Center": "675, -675",
      "Height": 187.0,
      "Width": 262.0,
      "Angle": -4.699299,
      "IsStatic": false
    }
  ],
  "Lines": [],
  "Springs": [
    {
      "A": "675, -225",
      "B": "675, -94"
    }
  ],
  "Triangles": []
}